Workbook

Sheet Start here
A1: Configure to WIN | B2B Pricing Execution Maturity Assessment
A2: Assess six dimensions of pricing execution maturity in B2B quoting and identify practical improvement priorities.
A3: This workbook is a focused module of the Configure to WIN Quote Performance Scan. It produces a dimension-level self-assessment, not an overall maturity score, industry benchmark or product recommendation.
A5: Purpose and scope
A6: What this assessment evaluates | B6: Pricing execution maturity across six dimensions: pricing data, agreement pricing, calculations, price execution, governance, and traceability.
A7: Who it is for | B7: B2B teams that create complex quotes and want a structured view of how pricing controls operate today and where practical improvement is needed.
A8: What the result contains | B8: A maturity level per dimension, current and optional target state, dimension gap, two weakest dimensions after completion, a recommended next control, and a current-versus-target profile.
A9: What the result does not contain | B9: No overall score, organisational maturity level, industry benchmark, comparison with other users, Quote Performance Score, or product/vendor recommendation.
A10: How answers work | B10: Select one of five descriptions. The label is converted to a value from 0 to 4 for dimension-level calculation only.
A11: Target state | B11: Target state is optional planning input. A dimension gap appears only when both current and target answers for that dimension are complete.
A13: Use the workbook in four steps
A14: 1 | B14: Complete all twelve current-state statements.
A15: 2 | B15: Add an optional target state.
A16: 3 | B16: Review the six dimension profiles and gaps.
A17: 4 | B17: Assign improvement actions and continue to the full Quote Performance Scan.
A19: Online resources
A20: Official assessment page | B20: https://configure.win/resources/pricing-maturity-assessment
A21: Full Quote Performance Scan | B21: https://configure.win/quote-performance-scan
A23: Asset name | B23: B2B Pricing Execution Maturity Assessment
A24: Version | B24: 1.0.0
A25: Last updated | B25: 2026-08-30
A27: Five answer options
A28: 0 — Ad hoc or manual | B28: The control is largely manual, informal or dependent on individual knowledge.
A29: 1 — Partly defined | B29: A control exists in parts of the process, but ownership or adoption is incomplete.
A30: 2 — Documented but inconsistent | B30: The control is documented and repeatable, but not applied consistently.
A31: 3 — System-supported and governed | B31: The control is supported by systems, governance and traceable execution.
A32: 4 — Measured and continuously improved | B32: The control is measured, reviewed and refined through an active feedback loop.

Sheet Quick assessment
A1: Configure to WIN | Quick assessment
A2: Rate twelve statements across six pricing-execution dimensions; add an optional target state and evidence notes.
A3: Complete all twelve current-state statements before interpreting priority rank. Target-state inputs are optional and no overall score is calculated.
A5: Assessment statements | K5: Assessment status
A6: Question | B6: Dimension | C6: Assessment statement | D6: Current state | E6: Current value | F6: Target state | G6: Target value | H6: Gap | I6: Evidence or notes | K6: Metric | L6: Calculated result
A7: 1 | B7: Pricing data foundation | C7: Current list, cost, floor and currency data is available before quoting begins. | E7: =IF(D7="","",VALUE(LEFT(D7,1))) | G7: =IF(F7="","",VALUE(LEFT(F7,1))) | H7: =IF(OR(E7="",G7=""),"",G7-E7) | K7: Current-state questions completed | L7: =COUNTIF(D7:D18,"<>") -> 0
A8: 2 | B8: Pricing data foundation | C8: Your team can identify the correct source and version of each commercial value. | E8: =IF(D8="","",VALUE(LEFT(D8,1))) | G8: =IF(F8="","",VALUE(LEFT(F8,1))) | H8: =IF(OR(E8="",G8=""),"",G8-E8) | K8: Target-state questions completed | L8: =COUNTIF(F7:F18,"<>") -> 0
A9: 3 | B9: Customer-specific and contracted pricing | C9: Current account- and product-specific price agreements are available inside the quote context. | E9: =IF(D9="","",VALUE(LEFT(D9,1))) | G9: =IF(F9="","",VALUE(LEFT(F9,1))) | H9: =IF(OR(E9="",G9=""),"",G9-E9) | K9: Assessment status | L9: =IF(L7=0,"Not started",IF(L7=12,"Complete","In progress — "&L7&" of 12 current-state statements completed")) -> Not started
A10: 4 | B10: Customer-specific and contracted pricing | C10: Deviations from existing customer prices are calculated explicitly. | E10: =IF(D10="","",VALUE(LEFT(D10,1))) | G10: =IF(F10="","",VALUE(LEFT(F10,1))) | H10: =IF(OR(E10="",G10=""),"",G10-E10) | K10: Current-state completeness warning | L10: =IF(L7=12,"","Complete all twelve current-state statements before interpreting the two weakest dimensions or priority rank.") -> Complete all twelve current-state statements before interpreting the two weakest dimensions or priority rank.
A11: 5 | B11: Calculations and deal economics | C11: Discounts, margins, rebates and incentives are calculated consistently. | E11: =IF(D11="","",VALUE(LEFT(D11,1))) | G11: =IF(F11="","",VALUE(LEFT(F11,1))) | H11: =IF(OR(E11="",G11=""),"",G11-E11)
A12: 6 | B12: Calculations and deal economics | C12: Sales, pricing and finance use the same commercial calculation logic. | E12: =IF(D12="","",VALUE(LEFT(D12,1))) | G12: =IF(F12="","",VALUE(LEFT(F12,1))) | H12: =IF(OR(E12="",G12=""),"",G12-E12) | K12: Answer scale
A13: 7 | B13: Price execution | C13: The applicable price is used consistently in each quote. | E13: =IF(D13="","",VALUE(LEFT(D13,1))) | G13: =IF(F13="","",VALUE(LEFT(F13,1))) | H13: =IF(OR(E13="",G13=""),"",G13-E13) | K13: 0 | L13: Ad hoc or manual
A14: 8 | B14: Price execution | C14: Manual price overrides remain visible and controlled. | E14: =IF(D14="","",VALUE(LEFT(D14,1))) | G14: =IF(F14="","",VALUE(LEFT(F14,1))) | H14: =IF(OR(E14="",G14=""),"",G14-E14) | K14: 1 | L14: Partly defined
A15: 9 | B15: Exception and approval governance | C15: Defined conditions determine when pricing approval is required. | E15: =IF(D15="","",VALUE(LEFT(D15,1))) | G15: =IF(F15="","",VALUE(LEFT(F15,1))) | H15: =IF(OR(E15="",G15=""),"",G15-E15) | K15: 2 | L15: Documented but inconsistent
A16: 10 | B16: Exception and approval governance | C16: Approval authority and routing are applied consistently. | E16: =IF(D16="","",VALUE(LEFT(D16,1))) | G16: =IF(F16="","",VALUE(LEFT(F16,1))) | H16: =IF(OR(E16="",G16=""),"",G16-E16) | K16: 3 | L16: System-supported and governed
A17: 11 | B17: Traceability and performance visibility | C17: Source values, calculations, rules and decisions can be reconstructed. | E17: =IF(D17="","",VALUE(LEFT(D17,1))) | G17: =IF(F17="","",VALUE(LEFT(F17,1))) | H17: =IF(OR(E17="",G17=""),"",G17-E17) | K17: 4 | L17: Measured and continuously improved
A18: 12 | B18: Traceability and performance visibility | C18: Management can identify recurring pricing exceptions, leakage and control gaps. | E18: =IF(D18="","",VALUE(LEFT(D18,1))) | G18: =IF(F18="","",VALUE(LEFT(F18,1))) | H18: =IF(OR(E18="",G18=""),"",G18-E18)

Sheet Maturity profile
A1: Configure to WIN | Maturity profile
A2: Review current and optional target maturity for each pricing-execution dimension, together with the planning gap and next control.
A3: Dimension averages appear only when both statements for that dimension are completed. Priority rank appears only after all twelve current-state responses are complete.
A5: Dimension profile | J5: Two weakest dimensions | X5: Dimension | Y5: Current | Z5: Target
A6: Dimension | B6: Current average | C6: Current level | D6: Target average | E6: Target level | F6: Gap | G6: Priority rank | H6: Recommended next control | J6: Priority | K6: Dimension | X6: Pricing data foundation | Y6: =B7 | Z6: =D7
A7: Pricing data foundation | B7: =IF(COUNTA('Quick assessment'!D7:D8)=2,AVERAGE('Quick assessment'!E7:E8),"") | C7: =IF(B7="","",IF(B7<0.8,"Reactive",IF(B7<1.6,"Emerging",IF(B7<2.4,"Established",IF(B7<3.2,"Advanced","Intelligent"))))) | D7: =IF(COUNTA('Quick assessment'!F7:F8)=2,AVERAGE('Quick assessment'!G7:G8),"") | E7: =IF(D7="","",IF(D7<0.8,"Reactive",IF(D7<1.6,"Emerging",IF(D7<2.4,"Established",IF(D7<3.2,"Advanced","Intelligent"))))) | F7: =IF(OR(B7="",D7=""),"",D7-B7) | G7: =IF(COUNTIF('Quick assessment'!D7:D18,"<>")<>12,"",1+COUNTIF($B$7:$B$12,"<"&B7)+COUNTIF($B$7:B7,B7)-1) | H7: =IF(C7="","",IF(C7="Reactive","Assign source ownership and define a minimum price-source register covering list, cost, floor and currency.",IF(C7="Emerging","Document and standardise source hierarchy, versioning and effective-date rules.",IF(C7="Established","Enforce source and version validation in the quote process and capture source exceptions.",IF(C7="Advanced","Measure stale, missing and conflicting source incidents and establish a review feedback loop.","Monitor source drift and continuously refine ownership, freshness thresholds and source controls."))))) | J7: 1 | K7: {=IF(COUNTIF('Quick assessment'!D7:D18,"<>")<>12,"",INDEX($A$7:$A$12,MATCH(1,$G$7:$G$12,0)))} | X7: Customer-specific and contracted pricing | Y7: =B8 | Z7: =D8
A8: Customer-specific and contracted pricing | B8: =IF(COUNTA('Quick assessment'!D9:D10)=2,AVERAGE('Quick assessment'!E9:E10),"") | C8: =IF(B8="","",IF(B8<0.8,"Reactive",IF(B8<1.6,"Emerging",IF(B8<2.4,"Established",IF(B8<3.2,"Advanced","Intelligent"))))) | D8: =IF(COUNTA('Quick assessment'!F9:F10)=2,AVERAGE('Quick assessment'!G9:G10),"") | E8: =IF(D8="","",IF(D8<0.8,"Reactive",IF(D8<1.6,"Emerging",IF(D8<2.4,"Established",IF(D8<3.2,"Advanced","Intelligent"))))) | F8: =IF(OR(B8="",D8=""),"",D8-B8) | G8: =IF(COUNTIF('Quick assessment'!D7:D18,"<>")<>12,"",1+COUNTIF($B$7:$B$12,"<"&B8)+COUNTIF($B$7:B8,B8)-1) | H8: =IF(C8="","",IF(C8="Reactive","Define ownership and a repeatable minimum control for recording active customer-specific and contracted prices.",IF(C8="Emerging","Document and standardise agreement applicability, effective dates and deviation calculation rules.",IF(C8="Established","Enforce agreement selection and deviation visibility systematically and capture exceptions.",IF(C8="Advanced","Measure agreement misses and deviations and establish a pricing review feedback loop.","Monitor agreement drift and continuously refine applicability, renewal and deviation controls."))))) | J8: 2 | K8: {=IF(COUNTIF('Quick assessment'!D7:D18,"<>")<>12,"",INDEX($A$7:$A$12,MATCH(2,$G$7:$G$12,0)))} | X8: Calculations and deal economics | Y8: =B9 | Z8: =D9
A9: Calculations and deal economics | B9: =IF(COUNTA('Quick assessment'!D11:D12)=2,AVERAGE('Quick assessment'!E11:E12),"") | C9: =IF(B9="","",IF(B9<0.8,"Reactive",IF(B9<1.6,"Emerging",IF(B9<2.4,"Established",IF(B9<3.2,"Advanced","Intelligent"))))) | D9: =IF(COUNTA('Quick assessment'!F11:F12)=2,AVERAGE('Quick assessment'!G11:G12),"") | E9: =IF(D9="","",IF(D9<0.8,"Reactive",IF(D9<1.6,"Emerging",IF(D9<2.4,"Established",IF(D9<3.2,"Advanced","Intelligent"))))) | F9: =IF(OR(B9="",D9=""),"",D9-B9) | G9: =IF(COUNTIF('Quick assessment'!D7:D18,"<>")<>12,"",1+COUNTIF($B$7:$B$12,"<"&B9)+COUNTIF($B$7:B9,B9)-1) | H9: =IF(C9="","",IF(C9="Reactive","Define ownership and a repeatable minimum calculation specification for discounts, margin, rebates and incentives.",IF(C9="Emerging","Document and standardise commercial calculation logic across sales, pricing and finance.",IF(C9="Established","Enforce shared calculation logic systematically and capture calculation exceptions.",IF(C9="Advanced","Measure calculation variance and deal-economics outcomes and establish a feedback loop.","Monitor calculation drift and continuously refine measures, assumptions and control thresholds."))))) | X9: Price execution | Y9: =B10 | Z9: =D10
A10: Price execution | B10: =IF(COUNTA('Quick assessment'!D13:D14)=2,AVERAGE('Quick assessment'!E13:E14),"") | C10: =IF(B10="","",IF(B10<0.8,"Reactive",IF(B10<1.6,"Emerging",IF(B10<2.4,"Established",IF(B10<3.2,"Advanced","Intelligent"))))) | D10: =IF(COUNTA('Quick assessment'!F13:F14)=2,AVERAGE('Quick assessment'!G13:G14),"") | E10: =IF(D10="","",IF(D10<0.8,"Reactive",IF(D10<1.6,"Emerging",IF(D10<2.4,"Established",IF(D10<3.2,"Advanced","Intelligent"))))) | F10: =IF(OR(B10="",D10=""),"",D10-B10) | G10: =IF(COUNTIF('Quick assessment'!D7:D18,"<>")<>12,"",1+COUNTIF($B$7:$B$12,"<"&B10)+COUNTIF($B$7:B10,B10)-1) | H10: =IF(C10="","",IF(C10="Reactive","Define ownership and a repeatable minimum control for applying the correct price and recording overrides.",IF(C10="Emerging","Document and standardise price-application and manual-override rules.",IF(C10="Established","Enforce price application and override capture systematically in the quote process.",IF(C10="Advanced","Measure override frequency and price-application exceptions and establish a review feedback loop.","Monitor execution drift and continuously refine override thresholds and price-application controls."))))) | J10: Chart note | X10: Exception and approval governance | Y10: =B11 | Z10: =D11
A11: Exception and approval governance | B11: =IF(COUNTA('Quick assessment'!D15:D16)=2,AVERAGE('Quick assessment'!E15:E16),"") | C11: =IF(B11="","",IF(B11<0.8,"Reactive",IF(B11<1.6,"Emerging",IF(B11<2.4,"Established",IF(B11<3.2,"Advanced","Intelligent"))))) | D11: =IF(COUNTA('Quick assessment'!F15:F16)=2,AVERAGE('Quick assessment'!G15:G16),"") | E11: =IF(D11="","",IF(D11<0.8,"Reactive",IF(D11<1.6,"Emerging",IF(D11<2.4,"Established",IF(D11<3.2,"Advanced","Intelligent"))))) | F11: =IF(OR(B11="",D11=""),"",D11-B11) | G11: =IF(COUNTIF('Quick assessment'!D7:D18,"<>")<>12,"",1+COUNTIF($B$7:$B$12,"<"&B11)+COUNTIF($B$7:B11,B11)-1) | H11: =IF(C11="","",IF(C11="Reactive","Define ownership, approval triggers and a repeatable minimum approval-authority control.",IF(C11="Emerging","Document and standardise approval conditions, authority and routing.",IF(C11="Established","Enforce approval logic systematically and capture approval and reapproval exceptions.",IF(C11="Advanced","Measure approval outcomes, delays and exception patterns and establish a feedback loop.","Monitor governance drift and continuously refine triggers, authority and routing controls."))))) | J11: Current and target are separate series. The target series appears only for dimensions with two completed target-state answers. | X11: Traceability and performance visibility | Y11: =B12 | Z11: =D12
A12: Traceability and performance visibility | B12: =IF(COUNTA('Quick assessment'!D17:D18)=2,AVERAGE('Quick assessment'!E17:E18),"") | C12: =IF(B12="","",IF(B12<0.8,"Reactive",IF(B12<1.6,"Emerging",IF(B12<2.4,"Established",IF(B12<3.2,"Advanced","Intelligent"))))) | D12: =IF(COUNTA('Quick assessment'!F17:F18)=2,AVERAGE('Quick assessment'!G17:G18),"") | E12: =IF(D12="","",IF(D12<0.8,"Reactive",IF(D12<1.6,"Emerging",IF(D12<2.4,"Established",IF(D12<3.2,"Advanced","Intelligent"))))) | F12: =IF(OR(B12="",D12=""),"",D12-B12) | G12: =IF(COUNTIF('Quick assessment'!D7:D18,"<>")<>12,"",1+COUNTIF($B$7:$B$12,"<"&B12)+COUNTIF($B$7:B12,B12)-1) | H12: =IF(C12="","",IF(C12="Reactive","Define ownership and a repeatable minimum decision trace for source values, calculations, rules and approvals.",IF(C12="Emerging","Document and standardise traceability requirements and recurring exception reporting.",IF(C12="Established","Enforce decision-trace capture systematically and retain reconstructable exception evidence.",IF(C12="Advanced","Measure recurring exceptions, leakage and control gaps and establish a management feedback loop.","Monitor traceability and leakage drift and continuously refine evidence, reporting and review controls.")))))

Sheet Maturity matrix
A1: Configure to WIN | Maturity matrix
A2: Use the matrix to interpret what each maturity level means within each pricing-execution dimension and what evidence can support the assessment.
A3: Descriptions are control-state examples, not industry benchmarks or prescribed policies.
A5: Dimension-specific maturity matrix
A6: Dimension | B6: Reactive | C6: Emerging | D6: Established | E6: Advanced | F6: Intelligent | G6: Examples of useful evidence
A7: Pricing data foundation | B7: Price inputs are gathered manually from people, files or systems with no consistently owned source hierarchy. | C7: Key sources are partly identified, but ownership, versions or effective dates are applied locally. | D7: List, cost, floor and currency sources are documented and repeatable, but quote-time enforcement is inconsistent. | E7: Approved sources, versions and effective dates are system-supported, governed and traceable in the quote process. | F7: Source freshness, conflicts and exceptions are measured, reviewed and continuously improved. | G7: Price-source register; effective-date history; source ownership record; currency source record.
A8: Customer-specific and contracted pricing | B8: Customer-specific or contracted prices are found manually and applicability depends on individual knowledge. | C8: Some agreement pricing is recorded, but coverage, dates or deviation handling vary by team or account. | D8: Agreement pricing and deviation rules are documented and repeatable, but not consistently enforced in every quote. | E8: Applicable agreements, effective dates and deviations are system-supported, governed and traceable. | F8: Agreement use, deviations, misses and renewal risks are measured, reviewed and continuously improved. | G8: Contracted-price record; customer-specific price history; applicability record; price-deviation evidence.
A9: Calculations and deal economics | B9: Discount, margin, rebate and incentive calculations are manual or differ by person or function. | C9: Core calculations are partly defined, but teams still use local spreadsheets, assumptions or logic. | D9: Commercial calculations are documented and repeatable, but enforcement and exception handling remain inconsistent. | E9: Shared calculation logic is system-supported, governed and traceable across sales, pricing and finance. | F9: Calculation variance and deal-economics outcomes are measured, reviewed and continuously improved. | G9: Calculation specification; worked calculation test; margin/rebate logic record; reconciliation evidence.
A10: Price execution | B10: The price used in a quote may be selected or overwritten manually without reliable visibility or control. | C10: Price-application and override practices exist, but are only partly defined or locally adopted. | D10: Price and override rules are documented and repeatable, but not consistently enforced. | E10: Applicable price selection and manual overrides are system-supported, governed and traceable. | F10: Override patterns, execution exceptions and realised outcomes are measured, reviewed and continuously improved. | G10: Applied-price trace; override log; override reason; released-quote evidence.
A11: Exception and approval governance | B11: Approval depends on judgement, email or person-to-person escalation with limited consistency. | C11: Some triggers and authority rules exist, but routing and reapproval are only partly standardised. | D11: Approval conditions and authority are documented and repeatable, but enforcement is inconsistent. | E11: Approval triggers, authority, routing and reapproval are system-supported, governed and traceable. | F11: Approval outcomes, delay patterns and governance exceptions are measured, reviewed and continuously improved. | G11: Approval policy; approval matrix; routing record; reapproval evidence; decision trace.
A12: Traceability and performance visibility | B12: Pricing decisions cannot be reliably reconstructed and recurring leakage or exceptions are largely anecdotal. | C12: Some evidence and reports exist, but traceability and performance visibility depend on local practices. | D12: Decision-trace and exception reporting requirements are documented and repeatable, but not consistently complete. | E12: Source values, calculations, rules, decisions and exceptions are system-supported, governed and traceable. | F12: Leakage, exception and control-gap trends are measured, reviewed and continuously improved. | G12: Decision trace; exception report; leakage analysis; control-gap review; management review record.

Sheet Improvement priorities
A1: Configure to WIN | Improvement priorities
A2: Turn the dimension profile into an action register without converting the assessment into an overall score.
A3: Priority rank is based on current-state dimension maturity after all twelve current responses are complete; use business context and evidence when assigning actions.
A5: Action register
A6: Priority | B6: Dimension | C6: Current level | D6: Target level | E6: Gap | F6: Recommended next control | G6: Action | H6: Owner | I6: Target date | J6: Status | K6: Evidence | L6: Notes
A7: =IF('Maturity profile'!G7="","",'Maturity profile'!G7) | B7: Pricing data foundation | C7: =IF('Maturity profile'!C7="","",'Maturity profile'!C7) | D7: =IF('Maturity profile'!E7="","",'Maturity profile'!E7) | E7: =IF('Maturity profile'!F7="","",'Maturity profile'!F7) | F7: =IF('Maturity profile'!H7="","",'Maturity profile'!H7)
A8: =IF('Maturity profile'!G8="","",'Maturity profile'!G8) | B8: Customer-specific and contracted pricing | C8: =IF('Maturity profile'!C8="","",'Maturity profile'!C8) | D8: =IF('Maturity profile'!E8="","",'Maturity profile'!E8) | E8: =IF('Maturity profile'!F8="","",'Maturity profile'!F8) | F8: =IF('Maturity profile'!H8="","",'Maturity profile'!H8)
A9: =IF('Maturity profile'!G9="","",'Maturity profile'!G9) | B9: Calculations and deal economics | C9: =IF('Maturity profile'!C9="","",'Maturity profile'!C9) | D9: =IF('Maturity profile'!E9="","",'Maturity profile'!E9) | E9: =IF('Maturity profile'!F9="","",'Maturity profile'!F9) | F9: =IF('Maturity profile'!H9="","",'Maturity profile'!H9)
A10: =IF('Maturity profile'!G10="","",'Maturity profile'!G10) | B10: Price execution | C10: =IF('Maturity profile'!C10="","",'Maturity profile'!C10) | D10: =IF('Maturity profile'!E10="","",'Maturity profile'!E10) | E10: =IF('Maturity profile'!F10="","",'Maturity profile'!F10) | F10: =IF('Maturity profile'!H10="","",'Maturity profile'!H10)
A11: =IF('Maturity profile'!G11="","",'Maturity profile'!G11) | B11: Exception and approval governance | C11: =IF('Maturity profile'!C11="","",'Maturity profile'!C11) | D11: =IF('Maturity profile'!E11="","",'Maturity profile'!E11) | E11: =IF('Maturity profile'!F11="","",'Maturity profile'!F11) | F11: =IF('Maturity profile'!H11="","",'Maturity profile'!H11)
A12: =IF('Maturity profile'!G12="","",'Maturity profile'!G12) | B12: Traceability and performance visibility | C12: =IF('Maturity profile'!C12="","",'Maturity profile'!C12) | D12: =IF('Maturity profile'!E12="","",'Maturity profile'!E12) | E12: =IF('Maturity profile'!F12="","",'Maturity profile'!F12) | F12: =IF('Maturity profile'!H12="","",'Maturity profile'!H12)
A14: How to use priorities
A15: Treat the automatically calculated rank and recommended next control as structured planning inputs. Record an action only after reviewing evidence, business risk, dependency and feasibility. A larger numeric gap does not automatically mean a higher business priority.

Sheet Quote Performance bridge
A1: Configure to WIN | Quote Performance bridge
A2: Connect the six pricing-execution dimensions to related Quote Performance themes without creating a score mapping.
A3: These are content relationships, not a one-to-one score mapping between this module and the full Quote Performance Scan.
A5: How pricing maturity connects to the wider quote process
A6: Pricing dimension | B6: Related Quote Performance themes | C6: Why the connection matters | D6: What the full scan adds
A7: Pricing data foundation | B7: Product & Price Data, Currency Control, Quote Accuracy | C7: Reliable pricing execution starts with controlled commercial source data before quote calculation and release. | D7: The full scan tests how source-data control interacts with quote creation, validation, cycle time and downstream visibility.
A8: Customer-specific and contracted pricing | B8: Product & Price Data, Commercial Control, Quote Accuracy | C8: Agreement applicability and explicit deviations determine whether customer commitments are applied accurately and governed. | D8: The full scan adds cross-process evidence on quote accuracy, approval logic, release efficiency and commercial visibility.
A9: Calculations and deal economics | B9: Commercial Control, True Deal Economics, Rebate Impact | C9: Shared calculation logic is necessary to understand the commercial outcome beyond list price and headline discount. | D9: The full scan adds quote-process measures, price-waterfall effects, rebate impact and visibility across the complete quote flow.
A10: Price execution | B10: Quote Accuracy, Commercial Control, Quote Release Efficiency | C10: Correct price application and controlled overrides connect pricing policy to what is actually released to the customer. | D10: The full scan adds validation, release-efficiency and cycle-time evidence to show how execution controls affect quote performance.
A11: Exception and approval governance | B11: Approval Logic, Quote Cycle Time, Delay Cause, Quote Release Efficiency | C11: Pricing governance can protect commercial thresholds but can also create delay when triggers, authority or routing are unclear. | D11: The full scan adds cycle-time, bottleneck and approval evidence to separate necessary control from avoidable friction.
A12: Traceability and performance visibility | B12: Commercial Visibility, Error Cause, Commercial Control, Rebate Impact | C12: A reconstructable decision trace and recurring exception visibility are prerequisites for diagnosing leakage and control gaps. | D12: The full scan adds end-to-end process measures so pricing evidence can be interpreted alongside accuracy, delay and commercial outcomes.
A14: Your pricing maturity profile shows where pricing execution needs attention. Complete the Quote Performance Scan to benchmark how pricing, quote creation, accuracy, cycle time, approvals and commercial visibility work together across the complete quote process.
A18: Full Quote Performance Scan | B18: https://configure.win/quote-performance-scan

Sheet Methodology
A1: Configure to WIN | Methodology
A2: Document the calculation logic, maturity boundaries, evidence approach and scope limitations used by this workbook.
A3: The methodology is designed for a focused self-assessment of six pricing dimensions; it does not provide an external benchmark or overall score.
A5: Assessment methodology
A6: Method element | B6: Definition | C6: Calculation or rule | D6: Blank handling | E6: Important limitation
A7: Dimensions | B7: Six separate pricing-execution dimensions. | C7: Each dimension is assessed independently. | D7: No result appears for a dimension until both current-state statements are completed. | E7: No average, sum or total score is calculated across the six dimensions.
A8: Statements | B8: Two equally weighted statements per dimension. | C8: Both statements contribute equally to the dimension average. | D8: A dimension average is blank if either statement is blank. | E8: Results reflect only entered answers.
A9: Answer values | B9: Five labels converted to numeric values 0 through 4. | C9: 0 Ad hoc/manual; 1 Partly defined; 2 Documented but inconsistent; 3 System-supported and governed; 4 Measured and continuously improved. | D9: A blank label remains blank; it is not treated as zero. | E9: The scale is an internal assessment scale, not a market benchmark.
A10: Current average | B10: Mean of the two current-state values within one dimension. | C10: (Statement 1 value + Statement 2 value) / 2. | D10: Blank until both current responses in the dimension are present. | E10: Current averages are not combined across dimensions.
A11: Target average | B11: Mean of the two optional target-state values within one dimension. | C11: (Target statement 1 value + Target statement 2 value) / 2. | D11: Blank until both target responses in the dimension are present. | E11: Target state is optional planning input.
A12: Maturity boundaries | B12: Reactive 0.00–0.79; Emerging 0.80–1.59; Established 1.60–2.39; Advanced 2.40–3.19; Intelligent 3.20–4.00. | C12: Level is derived from the applicable dimension average. | D12: No level is shown when the average is blank. | E12: A level is not an organisational maturity rating.
A13: Dimension gap | B13: Difference between optional target and current average for one dimension. | C13: Target average minus current average. | D13: Blank unless both current and target averages exist. | E13: Gaps are planning inputs only; they are not benefit estimates.
A14: Priority logic | B14: Weakest current-state dimensions are ranked after the current assessment is complete. | C14: Ascending current average; ties are broken by the fixed six-dimension order used in this workbook. | D14: All priority ranks remain blank until all twelve current-state responses are complete. | E14: Priority rank is not a substitute for business impact, risk or feasibility assessment.
A15: Recommended next control | B15: A transition control aligned to the dimension and its current maturity level. | C15: Reactive → define ownership and minimum control; Emerging → document and standardise; Established → enforce systematically and capture exceptions; Advanced → measure and establish feedback; Intelligent → monitor drift and refine. | D15: Blank if the current level is blank. | E15: No product or vendor is recommended.
A16: Evidence guidance | B16: Use observable records to support the selected response. | C16: Examples include price-source registers, effective-date history, contracted-price records, calculation specifications, override logs, approval policies, decision traces and exception reports. | D16: Evidence notes may remain blank, but unsupported responses should be treated cautiously. | E16: Existence of evidence alone does not prove control effectiveness.
A17: Data handling | B17: The workbook is a downloaded spreadsheet used locally by the user. | C17: No automatic transmission logic is included in the workbook. | D17: Not applicable. | E17: Use of the downloaded workbook does not automatically send data to Configure to WIN.
A19: Workbook information
A20: Version | B20: 1.0.0
A21: Publisher | B21: Configure to WIN
A22: Official online version | B22: https://configure.win/resources/pricing-maturity-assessment
A23: Last updated | B23: 2026-08-30
A24: Product/vendor recommendation | B24: None

Sheet Definitions
A1: Configure to WIN | Definitions
A2: Reference definitions for the pricing, governance and assessment terms used in the workbook.
A3: Definitions describe how terms are used in this assessment and are not legal, accounting or industry-standard prescriptions.
A5: Definitions and calculation notes
A6: Category | B6: Term | C6: Definition | D6: Calculation or use | E6: Important note
A7: Assessment concept | B7: Pricing execution maturity | C7: The degree to which pricing data, commercial calculations, price application, exceptions and evidence are controlled and improved during B2B quoting. | D7: Used as a dimension-level assessment concept; no overall organisational maturity level is calculated. | E7: A maturity level describes entered evidence against this workbook's scale, not an external benchmark.
A8: Price input | B8: List price | C8: The published or internally maintained reference price before customer-specific adjustments, discounts or other commercial effects. | D8: A controlled input that may serve as a starting point for price calculation. | E8: List price is not necessarily the price used or realised in a deal.
A9: Price input | B9: Cost | C9: The commercial cost basis used for margin or deal-economics calculations. | D9: Used in margin and profitability logic when applicable. | E9: The appropriate cost basis depends on the organisation's defined methodology.
A10: Price input | B10: Floor price | C10: A minimum permitted or review-triggering price threshold defined by commercial policy. | D10: Used as a validation or approval threshold. | E10: A floor is a governance input, not a market benchmark.
A11: Agreement pricing | B11: Customer-specific price | C11: A price explicitly defined for a particular account, customer segment or customer-product combination. | D11: Used when the agreement is applicable in the quote context. | E11: Applicability, version and effective date should be evidenced.
A12: Agreement pricing | B12: Contracted price | C12: A price or pricing condition established by a commercial contract or agreement. | D12: Used when the governing contract applies to the quoted item and date. | E12: Contract interpretation remains an organisational responsibility.
A13: Agreement pricing | B13: Price deviation | C13: The difference between an applicable reference or agreed price and the price proposed or used in the quote. | D13: Used to make departures from an expected price explicit. | E13: A deviation is not automatically an error; policy determines required action.
A14: Deal economics | B14: Discount | C14: A reduction from a defined reference price, expressed as an amount or percentage. | D14: Used in commercial calculations and, where applicable, approval logic. | E14: The reference price used for discount must be explicit.
A15: Deal economics | B15: Rebate | C15: A retrospective, conditional or off-invoice commercial amount that changes realised economics. | D15: Included where relevant to true deal economics. | E15: Eligibility, timing and accounting treatment can differ by programme.
A16: Deal economics | B16: Vendor incentive | C16: A supplier- or vendor-funded incentive that may affect expected deal economics. | D16: Included where relevant in expected cost or commercial outcome. | E16: Expected incentives should be distinguished from confirmed amounts.
A17: Deal economics | B17: Margin | C17: The commercial difference between revenue and the defined cost basis, expressed as an amount or percentage. | D17: Used to assess deal economics and governance thresholds. | E17: Margin depends on the selected revenue and cost definitions.
... A29: Evidence | B29: Evidence | C29: A document, record, system trace, sample, report or other observable artefact supporting the selected maturity description. | D29: Used to challenge assumptions and make assessment responses reviewable. | E29: Evidence quality and relevance should be considered, not only its existence.

Sheet Worked example
A1: Configure to WIN | Worked example
A2: A fictional industrial equipment distributor example showing completed responses, dimension results, priorities and example actions.
A3: Illustrative example — not customer data, benchmark data, advice or a recommended policy.
A5: Fictional completed assessment | K5: Calculated dimension results | X5: Dimension | Y5: Current | Z5: Target
A6: Question | B6: Dimension | C6: Assessment statement | D6: Current state | E6: Current value | F6: Target state | G6: Target value | H6: Gap | I6: Evidence or notes | K6: Dimension | L6: Current average | M6: Current level | N6: Target average | O6: Target level | P6: Gap | Q6: Priority rank | R6: Recommended next control | X6: Pricing data foundation | Y6: =L7 -> 1.5 | Z6: =N7 -> 3
A7: 1 | B7: Pricing data foundation | C7: Current list, cost, floor and currency data is available before quoting begins. | D7: 1 — Partly defined | E7: =IF(D7="","",VALUE(LEFT(D7,1))) -> 1 | F7: 3 — System-supported and governed | G7: =IF(F7="","",VALUE(LEFT(F7,1))) -> 3 | H7: =IF(OR(E7="",G7=""),"",G7-E7) -> 2 | I7: List and cost sources exist, but floor and currency ownership are partly manual. | K7: Pricing data foundation | L7: =IF(COUNTA(D7:D8)=2,AVERAGE(E7:E8),"") -> 1.5 | M7: =IF(L7="","",IF(L7<0.8,"Reactive",IF(L7<1.6,"Emerging",IF(L7<2.4,"Established",IF(L7<3.2,"Advanced","Intelligent"))))) -> Emerging | N7: =IF(COUNTA(F7:F8)=2,AVERAGE(G7:G8),"") -> 3 | O7: =IF(N7="","",IF(N7<0.8,"Reactive",IF(N7<1.6,"Emerging",IF(N7<2.4,"Established",IF(N7<3.2,"Advanced","Intelligent"))))) -> Advanced | P7: =IF(OR(L7="",N7=""),"",N7-L7) -> 1.5 | Q7: =IF(COUNTIF(D7:D18,"<>")<>12,"",1+COUNTIF($L$7:$L$12,"<"&L7)+COUNTIF($L$7:L7,L7)-1) -> 3 | R7: =IF(M7="","",IF(M7="Reactive","Assign source ownership and define a minimum price-source register covering list, cost, floor and currency.",IF(M7="Emerging","Document and standardise source hierarchy, versioning and effective-date rules.",IF(M7="Established","Enforce source and version validation in the quote process and capture source exceptions.",IF(M7="Advanced","Measure stale, missing and conflicting source incidents and establish a review feedback loop.","Monitor source drift and continuously refine ownership, freshness thresholds and source controls."))))) -> Document and standardise source hierarchy, versioning and effective-date rules. | X7: Customer-specific and contracted pricing | Y7: =L8 -> 1 | Z7: =N8 -> 3
A8: 2 | B8: Pricing data foundation | C8: Your team can identify the correct source and version of each commercial value. | D8: 2 — Documented but inconsistent | E8: =IF(D8="","",VALUE(LEFT(D8,1))) -> 2 | F8: 3 — System-supported and governed | G8: =IF(F8="","",VALUE(LEFT(F8,1))) -> 3 | H8: =IF(OR(E8="",G8=""),"",G8-E8) -> 1 | I8: ERP and pricing workbook versions are documented but not always reconciled before quoting. | K8: Customer-specific and contracted pricing | L8: =IF(COUNTA(D9:D10)=2,AVERAGE(E9:E10),"") -> 1 | M8: =IF(L8="","",IF(L8<0.8,"Reactive",IF(L8<1.6,"Emerging",IF(L8<2.4,"Established",IF(L8<3.2,"Advanced","Intelligent"))))) -> Emerging | N8: =IF(COUNTA(F9:F10)=2,AVERAGE(G9:G10),"") -> 3 | O8: =IF(N8="","",IF(N8<0.8,"Reactive",IF(N8<1.6,"Emerging",IF(N8<2.4,"Established",IF(N8<3.2,"Advanced","Intelligent"))))) -> Advanced | P8: =IF(OR(L8="",N8=""),"",N8-L8) -> 2 | Q8: =IF(COUNTIF(D7:D18,"<>")<>12,"",1+COUNTIF($L$7:$L$12,"<"&L8)+COUNTIF($L$7:L8,L8)-1) -> 2 | R8: =IF(M8="","",IF(M8="Reactive","Define ownership and a repeatable minimum control for recording active customer-specific and contracted prices.",IF(M8="Emerging","Document and standardise agreement applicability, effective dates and deviation calculation rules.",IF(M8="Established","Enforce agreement selection and deviation visibility systematically and capture exceptions.",IF(M8="Advanced","Measure agreement misses and deviations and establish a pricing review feedback loop.","Monitor agreement drift and continuously refine applicability, renewal and deviation controls."))))) -> Document and standardise agreement applicability, effective dates and deviation calculation rules. | X8: Calculations and deal economics | Y8: =L9 -> 2.5 | Z8: =N9 -> 3.5
A9: 3 | B9: Customer-specific and contracted pricing | C9: Current account- and product-specific price agreements are available inside the quote context. | D9: 1 — Partly defined | E9: =IF(D9="","",VALUE(LEFT(D9,1))) -> 1 | F9: 3 — System-supported and governed | G9: =IF(F9="","",VALUE(LEFT(F9,1))) -> 3 | H9: =IF(OR(E9="",G9=""),"",G9-E9) -> 2 | I9: Contract prices are stored by account, but product coverage and effective dates require manual checking. | K9: Calculations and deal economics | L9: =IF(COUNTA(D11:D12)=2,AVERAGE(E11:E12),"") -> 2.5 | M9: =IF(L9="","",IF(L9<0.8,"Reactive",IF(L9<1.6,"Emerging",IF(L9<2.4,"Established",IF(L9<3.2,"Advanced","Intelligent"))))) -> Advanced | N9: =IF(COUNTA(F11:F12)=2,AVERAGE(G11:G12),"") -> 3.5 | O9: =IF(N9="","",IF(N9<0.8,"Reactive",IF(N9<1.6,"Emerging",IF(N9<2.4,"Established",IF(N9<3.2,"Advanced","Intelligent"))))) -> Intelligent | P9: =IF(OR(L9="",N9=""),"",N9-L9) -> 1 | Q9: =IF(COUNTIF(D7:D18,"<>")<>12,"",1+COUNTIF($L$7:$L$12,"<"&L9)+COUNTIF($L$7:L9,L9)-1) -> 6 | R9: =IF(M9="","",IF(M9="Reactive","Define ownership and a repeatable minimum calculation specification for discounts, margin, rebates and incentives.",IF(M9="Emerging","Document and standardise commercial calculation logic across sales, pricing and finance.",IF(M9="Established","Enforce shared calculation logic systematically and capture calculation exceptions.",IF(M9="Advanced","Measure calculation variance and deal-economics outcomes and establish a feedback loop.","Monitor calculation drift and continuously refine measures, assumptions and control thresholds."))))) -> Measure calculation variance and deal-economics outcomes and establish a feedback loop. | X9: Price execution | Y9: =L10 -> 2 | Z9: =N10 -> 3
A10: 4 | B10: Customer-specific and contracted pricing | C10: Deviations from existing customer prices are calculated explicitly. | D10: 1 — Partly defined | E10: =IF(D10="","",VALUE(LEFT(D10,1))) -> 1 | F10: 3 — System-supported and governed | G10: =IF(F10="","",VALUE(LEFT(F10,1))) -> 3 | H10: =IF(OR(E10="",G10=""),"",G10-E10) -> 2 | I10: Deviation from the last contracted price is visible only when the salesperson adds it manually. | K10: Price execution | L10: =IF(COUNTA(D13:D14)=2,AVERAGE(E13:E14),"") -> 2 | M10: =IF(L10="","",IF(L10<0.8,"Reactive",IF(L10<1.6,"Emerging",IF(L10<2.4,"Established",IF(L10<3.2,"Advanced","Intelligent"))))) -> Established | N10: =IF(COUNTA(F13:F14)=2,AVERAGE(G13:G14),"") -> 3 | O10: =IF(N10="","",IF(N10<0.8,"Reactive",IF(N10<1.6,"Emerging",IF(N10<2.4,"Established",IF(N10<3.2,"Advanced","Intelligent"))))) -> Advanced | P10: =IF(OR(L10="",N10=""),"",N10-L10) -> 1 | Q10: =IF(COUNTIF(D7:D18,"<>")<>12,"",1+COUNTIF($L$7:$L$12,"<"&L10)+COUNTIF($L$7:L10,L10)-1) -> 5 | R10: =IF(M10="","",IF(M10="Reactive","Define ownership and a repeatable minimum control for applying the correct price and recording overrides.",IF(M10="Emerging","Document and standardise price-application and manual-override rules.",IF(M10="Established","Enforce price application and override capture systematically in the quote process.",IF(M10="Advanced","Measure override frequency and price-application exceptions and establish a review feedback loop.","Monitor execution drift and continuously refine override thresholds and price-application controls."))))) -> Enforce price application and override capture systematically in the quote process. | X10: Exception and approval governance | Y10: =L11 -> 1.5 | Z10: =N11 -> 3
A11: 5 | B11: Calculations and deal economics | C11: Discounts, margins, rebates and incentives are calculated consistently. | D11: 2 — Documented but inconsistent | E11: =IF(D11="","",VALUE(LEFT(D11,1))) -> 2 | F11: 3 — System-supported and governed | G11: =IF(F11="","",VALUE(LEFT(F11,1))) -> 3 | H11: =IF(OR(E11="",G11=""),"",G11-E11) -> 1 | I11: Discount and margin logic is documented; rebate treatment is less consistent. | K11: Exception and approval governance | L11: =IF(COUNTA(D15:D16)=2,AVERAGE(E15:E16),"") -> 1.5 | M11: =IF(L11="","",IF(L11<0.8,"Reactive",IF(L11<1.6,"Emerging",IF(L11<2.4,"Established",IF(L11<3.2,"Advanced","Intelligent"))))) -> Emerging | N11: =IF(COUNTA(F15:F16)=2,AVERAGE(G15:G16),"") -> 3 | O11: =IF(N11="","",IF(N11<0.8,"Reactive",IF(N11<1.6,"Emerging",IF(N11<2.4,"Established",IF(N11<3.2,"Advanced","Intelligent"))))) -> Advanced | P11: =IF(OR(L11="",N11=""),"",N11-L11) -> 1.5 | Q11: =IF(COUNTIF(D7:D18,"<>")<>12,"",1+COUNTIF($L$7:$L$12,"<"&L11)+COUNTIF($L$7:L11,L11)-1) -> 4 | R11: =IF(M11="","",IF(M11="Reactive","Define ownership, approval triggers and a repeatable minimum approval-authority control.",IF(M11="Emerging","Document and standardise approval conditions, authority and routing.",IF(M11="Established","Enforce approval logic systematically and capture approval and reapproval exceptions.",IF(M11="Advanced","Measure approval outcomes, delays and exception patterns and establish a feedback loop.","Monitor governance drift and continuously refine triggers, authority and routing controls."))))) -> Document and standardise approval conditions, authority and routing. | X11: Traceability and performance visibility | Y11: =L12 -> 0.5 | Z11: =N12 -> 3
A12: 6 | B12: Calculations and deal economics | C12: Sales, pricing and finance use the same commercial calculation logic. | D12: 3 — System-supported and governed | E12: =IF(D12="","",VALUE(LEFT(D12,1))) -> 3 | F12: 4 — Measured and continuously improved | G12: =IF(F12="","",VALUE(LEFT(F12,1))) -> 4 | H12: =IF(OR(E12="",G12=""),"",G12-E12) -> 1 | I12: Finance and pricing share a governed calculation specification used by the quoting tool. | K12: Traceability and performance visibility | L12: =IF(COUNTA(D17:D18)=2,AVERAGE(E17:E18),"") -> 0.5 | M12: =IF(L12="","",IF(L12<0.8,"Reactive",IF(L12<1.6,"Emerging",IF(L12<2.4,"Established",IF(L12<3.2,"Advanced","Intelligent"))))) -> Reactive | N12: =IF(COUNTA(F17:F18)=2,AVERAGE(G17:G18),"") -> 3 | O12: =IF(N12="","",IF(N12<0.8,"Reactive",IF(N12<1.6,"Emerging",IF(N12<2.4,"Established",IF(N12<3.2,"Advanced","Intelligent"))))) -> Advanced | P12: =IF(OR(L12="",N12=""),"",N12-L12) -> 2.5 | Q12: =IF(COUNTIF(D7:D18,"<>")<>12,"",1+COUNTIF($L$7:$L$12,"<"&L12)+COUNTIF($L$7:L12,L12)-1) -> 1 | R12: =IF(M12="","",IF(M12="Reactive","Define ownership and a repeatable minimum decision trace for source values, calculations, rules and approvals.",IF(M12="Emerging","Document and standardise traceability requirements and recurring exception reporting.",IF(M12="Established","Enforce decision-trace capture systematically and retain reconstructable exception evidence.",IF(M12="Advanced","Measure recurring exceptions, leakage and control gaps and establish a management feedback loop.","Monitor traceability and leakage drift and continuously refine evidence, reporting and review controls."))))) -> Define ownership and a repeatable minimum decision trace for source values, calculations, rules and approvals.
A13: 7 | B13: Price execution | C13: The applicable price is used consistently in each quote. | D13: 2 — Documented but inconsistent | E13: =IF(D13="","",VALUE(LEFT(D13,1))) -> 2 | F13: 3 — System-supported and governed | G13: =IF(F13="","",VALUE(LEFT(F13,1))) -> 3 | H13: =IF(OR(E13="",G13=""),"",G13-E13) -> 1 | I13: Standard price selection is repeatable, but some contract cases require manual confirmation.
A14: 8 | B14: Price execution | C14: Manual price overrides remain visible and controlled. | D14: 2 — Documented but inconsistent | E14: =IF(D14="","",VALUE(LEFT(D14,1))) -> 2 | F14: 3 — System-supported and governed | G14: =IF(F14="","",VALUE(LEFT(F14,1))) -> 3 | H14: =IF(OR(E14="",G14=""),"",G14-E14) -> 1 | I14: Overrides are visible in quote history but reasons are not always structured. | K14: Two example priorities
A15: 9 | B15: Exception and approval governance | C15: Defined conditions determine when pricing approval is required. | D15: 1 — Partly defined | E15: =IF(D15="","",VALUE(LEFT(D15,1))) -> 1 | F15: 3 — System-supported and governed | G15: =IF(F15="","",VALUE(LEFT(F15,1))) -> 3 | H15: =IF(OR(E15="",G15=""),"",G15-E15) -> 2 | I15: Discount and margin triggers exist but some exception categories depend on judgement. | K15: Priority | L15: Dimension
A16: 10 | B16: Exception and approval governance | C16: Approval authority and routing are applied consistently. | D16: 2 — Documented but inconsistent | E16: =IF(D16="","",VALUE(LEFT(D16,1))) -> 2 | F16: 3 — System-supported and governed | G16: =IF(F16="","",VALUE(LEFT(F16,1))) -> 3 | H16: =IF(OR(E16="",G16=""),"",G16-E16) -> 1 | I16: Approval authority is documented; routing for substitutes and escalations is partly manual. | K16: 1 | L16: {=INDEX($K$7:$K$12,MATCH(1,$Q$7:$Q$12,0))} -> Traceability and performance visibility
A17: 11 | B17: Traceability and performance visibility | C17: Source values, calculations, rules and decisions can be reconstructed. | D17: 0 — Ad hoc or manual | E17: =IF(D17="","",VALUE(LEFT(D17,1))) -> 0 | F17: 3 — System-supported and governed | G17: =IF(F17="","",VALUE(LEFT(F17,1))) -> 3 | H17: =IF(OR(E17="",G17=""),"",G17-E17) -> 3 | I17: Source and decision history is incomplete across ERP, email approval and the quoting tool. | K17: 2 | L17: {=INDEX($K$7:$K$12,MATCH(2,$Q$7:$Q$12,0))} -> Customer-specific and contracted pricing
A18: 12 | B18: Traceability and performance visibility | C18: Management can identify recurring pricing exceptions, leakage and control gaps. | D18: 1 — Partly defined | E18: =IF(D18="","",VALUE(LEFT(D18,1))) -> 1 | F18: 3 — System-supported and governed | G18: =IF(F18="","",VALUE(LEFT(F18,1))) -> 3 | H18: =IF(OR(E18="",G18=""),"",G18-E18) -> 2 | I18: Exception reporting is periodic and does not consistently isolate recurring leakage patterns.
K36: Illustrative action examples
K37: Priority | L37: Dimension | M37: Example action | N37: Owner | O37: Target date | P37: Status | Q37: Evidence | R37: Notes
K38: 1 | L38: =L16 -> Traceability and performance visibility | M38: Create a minimum decision trace linking source values, calculation output, pricing exceptions and approval decisions for released quotes. | N38: Commercial operations | O38: 2026-10-15 | P38: Planned | Q38: Decision-trace sample and monthly exception report | R38: Pilot on high-value equipment quotes before wider rollout.
K39: 2 | L39: =L17 -> Customer-specific and contracted pricing | M39: Standardise contracted-price applicability and effective-date checks and make price deviation explicit in the quote review step. | N39: Pricing | O39: 2026-09-30 | P39: In progress | Q39: Contracted-price record and deviation test cases | R39: Start with top contracted accounts and expand after exception review.
